[
    { "name": "Video URI", "tagtype": "alphanumerical", "tags": [] },
    { "name": "Duration (sec)", "tagtype": "numerical_dec", "tags": [] },
    { "name": "fps", "tagtype": "numerical_dec", "tags": [] },
    { "name": "Camera", "tagtype": "alphanumerical", "tags": [] },
    { "name": "Album", "tagtype": "alphanumerical", "tags": ["Family", "Vacation 2023"] },
    { "name": "Start (hh:mm:ss)", "tagtype": "time", "tags": ["00:00:00", "00:01:30"] },
    { "name": "End (hh:mm:ss)", "tagtype": "time", "tags": [] },
    { "name": "Start (sec)", "tagtype": "numerical_dec", "tags": [] },
    { "name": "End (sec)", "tagtype": "numerical_dec", "tags": [] },
    { "name": "Start (frame)", "tagtype": "numerical_int", "tags": [] },
    { "name": "End (frame)", "tagtype": "numerical_int", "tags": [] },
    { "name": "Keyframe frame", "tagtype": "numerical_int", "tags": [] },
    { "name": "Keyframe (sec)", "tagtype": "numerical_dec", "tags": [] },
    { "name": "Keyframe (hh:mm:ss)", "tagtype": "time", "tags": [] },
    { "name": "Keyframe filename", "tagtype": "alphanumerical", "tags": [] },
    { "name": "Day", "tagtype": "numerical_int", "tags": [] },
    { "name": "Hour", "tagtype": "numerical_int", "tags": [0, 1, 2, 3, 4, 10, 11, 12] },
    { "name": "Person", "tagtype": "alphanumerical", "tags": [] },
    { "name": "Transcript", "tagtype": "alphanumerical", "tags": [] },
    { "name": "Caption", "tagtype": "alphanumerical", "tags": [] },
    { "name": "Objects", "tagtype": "alphanumerical", "tags": [] },
    { "name": "Categories", "tagtype": "alphanumerical", "tags": [] },
    { "name": "User Tags", "tagtype": "alphanumerical", "tags": [] },
    { "name": "Segment_Caption_Index_Id", "tagtype": "numerical_int", "tags": [] },
    { "name": "Clip_Index_Id", "tagtype": "numerical_int", "tags": [] },
    { "name": "Caption_KF_Index_Id", "tagtype": "numerical_int", "tags": [] },
    { "name": "Transcript_Index_Id", "tagtype": "numerical_int", "tags": [] },
    { "name": "Closest_Keyframe", "tagtype": "alphanumerical", "tags": [] }
]